[
  {
  "nome": "Stefano Di Lena",
  "soprannome": "STEPH",
  "numero": 7,
  "foto": "asset/steph.jpg"
  },
  {
    "nome": "Marco Accetta",
    "soprannome": "",
    "numero": 45,
    "foto": "asset/accetta.jpg"
  },
  {
  "nome": "Mauro Origlia",
  "soprannome": "",
  "numero": 10,
  "foto": "asset/origlia.jpg"
  },
  {
  "nome": "Vincenzo Russo",
  "soprannome": "VINNI",
  "numero": 1,
  "foto": "asset/vinni.jpg"
  },
  {
  "nome": "Luigi Daniele Barbone",
  "soprannome": "MANDELA",
  "numero": 16,
  "foto": "asset/a.jpg"
  },
  {
  "nome": "Mario Mezzina",
  "soprannome": "",
  "numero": 29,
  "foto": "asset/a.jpg"
  },
  {
  "nome": "Alessandro Solazzo",
  "soprannome": "",
  "numero": 8,
  "foto": "asset/solazzo.jpg"
  },
  {
  "nome": "Giovanni Meuli",
  "soprannome": "",
  "numero": 5,
  "foto": "asset/a.jpg"
  },
  {
  "nome": "Manuel Flores",
  "soprannome": "",
  "numero": 11,
  "foto": "asset/flores.jpg"
  },
  {
  "nome": "Alessandro Guerra",
  "soprannome": "",
  "numero": 1,
  "foto": "asset/guerra0.jpg"
  },
  {
  "nome": "Mario Rizzo",
  "soprannome": "",
  "numero": 6,
  "foto": "asset/a.jpg"
  },
  {
  "nome": "Fabiano Tafaro",
  "soprannome": "",
  "numero": 11,
  "foto": "asset/a.jpg"
  },
  {
  "nome": "Gabriele Ferrandino",
  "soprannome": "",
  "numero": 2,
  "foto": "asset/ferrandino.jpg"
  },
  {
  "nome": "Antonio Iasiello",
  "soprannome": "IL MICIO",
  "numero": 77,
  "foto": "asset/micio.jpg"
  },
  {
  "nome": "Matteo Sembenini",
  "soprannome": "SEMBE",
  "numero": 7,
  "foto": "asset/sembe.jpg"
  },
  {
  "nome": "JJ Zigrino",
  "soprannome": "MULTIGOAL",
  "numero": "2-5",
  "foto": "asset/jj.jpg"
  },
  {
  "nome": "Flavio Carbone",
  "soprannome": "",
  "numero": 10,
  "foto": "asset/a.jpg"
  },
  {
  "nome": "Antonio Fuzio",
  "soprannome": "",
  "numero": 69,
  "foto": "asset/fuzio.jpg"
  },
  {
  "nome": "Pierluigi De Marco",
  "soprannome": "",
  "numero": 1,
  "foto": "asset/pier.jpg"
  },
  {
  "nome": "Michele Scoppio",
  "soprannome": "BOOM BOOM",
  "numero": 88,
  "foto": "asset/boom.jpg"
  },
  {
  "nome": "Fabrizio Lorini",
  "soprannome": "FABRI",
  "numero": 8,
  "foto": "asset/a.jpg"
  },
  {
  "nome": "Andrea Fundone",
  "soprannome": "",
  "numero": 69,
  "foto": "asset/fundone.jpg"
  },
  {
  "nome": "Luigi Vaira",
  "soprannome": "",
  "numero": 24,
  "foto": "asset/vaira.jpg"
  },
  {
  "nome": "Lorenzo Milfa",
  "soprannome": "",
  "numero": 10,
  "foto": "asset/milfa.jpg"
  },
  {
  "nome": "Lorenzo Gentile",
  "soprannome": "TEMPESTA",
  "numero": 9,
  "foto": "asset/tempesta.jpg"
  },
  {
  "nome": "Domenico Jr. Centrone",
  "soprannome": "DODINHO JR",
  "numero": 7,
  "foto": "asset/dodo.jpg"
  },
  {
  "nome": "Alessandro del Giudice",
  "soprannome": "",
  "numero": 17,
  "foto": "asset/giudice.jpg"
  },
  {
  "nome": "Carlo Basile",
  "soprannome": "",
  "numero": 27,
  "foto": "asset/basile.jpg"
  },
  {
  "nome": "Gabriele Maci",
  "soprannome": "",
  "numero": "00",
  "foto": "asset/maci.jpg"
  },
  {
  "nome": "Gianluca Audiello",
  "soprannome": "JL",
  "numero": 15,
  "foto": "asset/jl.jpg"
  },
  {
  "nome": "Giuseppe Pepe",
  "soprannome": "PEPS",
  "numero": 27,
  "foto": "asset/peps.jpg"
  },
  {
  "nome": "Cataldo Sapio",
  "soprannome": "FROSTE",
  "numero": 6,
  "foto": "asset/aldo.jpg"
  },
  {
  "nome": "Marco Montrano",
  "soprannome": "SHARP",
  "numero": 22,
  "foto": "asset/montrano.jpg"
  },
  {
  "nome": "Riccardo Roscica",
  "soprannome": "ROSCIRIC",
  "numero": 28,
  "foto": "asset/a.jpeg"
  },
  {
  "nome": "Cosimo D'Onghia",
  "soprannome": "MIMINHO",
  "numero": 9,
  "foto": "asset/miminho.jpg"
  },
  {
  "nome": "Adriano Pio Darcangelo",
  "soprannome": "DRAI",
  "numero": 18,
  "foto": "asset/a.jpg"
  },
  {
  "nome": "Michele Ventola",
  "soprannome": "O'TRAK",
  "numero": 10,
  "foto": "asset/ventola.jpg"
  },
  {
  "nome": "Matia Shehu",
  "soprannome": "",
  "numero": 13,
  "foto": "asset/a.jpg"
  },
  {
  "nome": "Luca Padovano",
  "soprannome": "",
  "numero": 7,
  "foto": "asset/padovano.jpg"
  },
  {
  "nome": "Francesco Albanese",
  "soprannome": "",
  "numero": 20,
  "foto": "asset/a.jpg"
  },
  {
  "nome": "Francesco Santamaria",
  "soprannome": "SANTACLAUS",
  "numero": 69,
  "foto": "asset/santamaria.jpg"
  },
  {
  "nome": "Stefano Vidali",
  "soprannome": "",
  "numero": 2,
  "foto": "asset/a.jpg"
  },
  {
  "nome": "Gianluca Chiappinelli",
  "soprannome": "",
  "numero": 10,
  "foto": "asset/chiaps.jpg"
  },
  {
  "nome": "Marco Amodio",
  "soprannome": "",
  "numero": 11,
  "foto": "asset/amodio.jpg"
  },
  {
  "nome": "Raffaele Guerra",
  "soprannome": "",
  "numero": 9,
  "foto": "asset/lele.jpg"
  },
  {
  "nome": "Andrea Capuzzolo",
  "soprannome": "",
  "numero": 90,
  "foto": "asset/a.jpg"
  },
  {
  "nome": "Mattia Mavelli",
  "soprannome": "",
  "numero": 22,
  "foto": "asset/a.jpg"
  },
  {
  "nome": "Pasquale Iannelli",
  "soprannome": "",
  "numero": 1,
  "foto": "asset/paki.jpg"
  },
  {
  "nome": "Matteo Daniele",
  "soprannome": "MATT DANIEL'S",
  "numero": 45,
  "foto": "asset/matts.jpg"
  },
  {
  "nome": "Gerardo Valerio Teutonico",
  "soprannome": "GERRYNHO",
  "numero": 27,
  "foto": "asset/gerry.jpg"
  },
  {
  "nome": "Giovanni Corso",
  "soprannome": "",
  "numero": 3,
  "foto": "asset/a.jpeg"
  },
  {
  "nome": "Gabriele Pedacchio",
  "soprannome": "PEDAC",
  "numero": 14,
  "foto": "asset/pedac.jpg"
  },
  {
  "nome": "Mattia Ieva",
  "soprannome": "",
  "numero": 21,
  "foto": "asset/ieva.jpg"
  },
  {
  "nome": "Daniel Sandu",
  "soprannome": "ASSOKAPPA",
  "numero": "7-2",
  "foto": "asset/a.jpg"
  },
  {
  "nome": "Angelo Anatilopan",
  "soprannome": "",
  "numero": 9,
  "foto": "asset/antiltop.jpg"
  },
  {
  "nome": "Dylan Todisco",
  "soprannome": "SMITH",
  "numero": 10,
  "foto": "asset/dylan.jpg"
  },
  {
  "nome": "Mattia Pandolfi",
  "soprannome": "",
  "numero": 11,
  "foto": "asset/pandolfi.jpg"
  }
]
