[
  {
  "giornata": 1,
  "squadraCasa": "Wild Boys",
  "squadraOspite": "Imp",
  "golCasa": null,
  "golOspite": null,
  "status": "da giocare",
  "vincitoreShootout": null, 
  "data": "31/03", "ora": "20:00"
  },
  {
    "giornata": 1,
    "squadraCasa": "I Trogloditi",
    "squadraOspite": "Levante X",
    "golCasa": null,
    "golOspite": null,
    "status": "da giocare",
    "vincitoreShootout": null, 
    "data": "31/03", "ora": "20:40"
  },
  {
    "giornata": 1,
    "squadraCasa": "I Pomodorini",
    "squadraOspite": "Sangu FC",
    "golCasa": null,
    "golOspite": null,
    "status": "da giocare",
    "vincitoreShootout": null,
    "data": "31/03", "ora": "21:20"
  },
  {
    "giornata": 2,
    "squadraCasa": "Imp",
    "squadraOspite": "Sangu FC",
    "golCasa": null,
    "golOspite": null,
    "status": "da giocare",
    "vincitoreShootout": null,
    "data": "aprile", "ora": "!"
  },
  {
    "giornata": 2,
    "squadraCasa": "Levante X",
    "squadraOspite": "I Pomodorini",
    "golCasa": null,
    "golOspite": null,
    "status": "da giocare",
    "vincitoreShootout": null,
    "data": "aprile", "ora": "!"
  },
  {
    "giornata": 2,
    "squadraCasa": "Wild Boys",
    "squadraOspite": "I Trogloditi",
    "golCasa": null,
    "golOspite": null,
    "status": "da giocare",
    "vincitoreShootout": null,
    "data": "aprile", "ora": "!"
  },
  {
    "giornata": 3,
    "squadraCasa": "I Trogloditi",
    "squadraOspite": "Imp",
    "golCasa": null,
    "golOspite": null,
    "status": "da giocare",
    "vincitoreShootout": null,
    "data": "maggio", "ora": "!"
  },
  {
    "giornata": 3,
    "squadraCasa": "Wild Boys",
    "squadraOspite": "I Pomodorini",
    "golCasa": null,
    "golOspite": null,
    "status": "da giocare",
    "vincitoreShootout": null,
    "data": "maggio", "ora": "!"
  },
  {
    "giornata": 3,
    "squadraCasa": "Sangu FC",
    "squadraOspite": "Levante X",
    "golCasa": null,
    "golOspite": null,
    "status": "da giocare",
    "vincitoreShootout": null,
    "data": "maggio", "ora": "!"
  },
  {
    "giornata": 4,
    "squadraCasa": "Imp",
    "squadraOspite": "Levante X",
    "golCasa": null,
    "golOspite": null,
    "status": "da giocare",
    "vincitoreShootout": null,
    "data": "giugno", "ora": "!"
  },
  {
    "giornata": 4,
    "squadraCasa": "Sangu FC",
    "squadraOspite": "Wild Boys",
    "golCasa": null,
    "golOspite": null,
    "status": "da giocare",
    "vincitoreShootout": null,
    "data": "giugno", "ora": "!"
  },
  {
    "giornata": 4,
    "squadraCasa": "I Trogloditi",
    "squadraOspite": "I Pomodorini",
    "golCasa": null,
    "golOspite": null,
    "status": "da giocare",
    "vincitoreShootout": null,
    "data": "giugno", "ora": "!"
  },
  {
    "giornata": 5,
    "squadraCasa": "Imp",
    "squadraOspite": "I Pomodorini",
    "golCasa": null,
    "golOspite": null,
    "status": "da giocare",
    "vincitoreShootout": null,
    "data": "luglio", "ora": "!"
  },
  {
    "giornata": 5,
    "squadraCasa": "Sangu FC",
    "squadraOspite": "I Trogloditi",
    "golCasa": null,
    "golOspite": null,
    "status": "da giocare",
    "vincitoreShootout": null,
    "data": "luglio", "ora": "!"
  },
  {
    "giornata": 5,
    "squadraCasa": "Levante X",
    "squadraOspite": "Wild Boys",
    "golCasa": null,
    "golOspite": null,
    "status": "da giocare",
    "vincitoreShootout": null,
    "data": "luglio", "ora": "!"
  }
]
